{
  "posts": [
    {
      "id": 1,
      "name": "Behaviour Driven Development with Javascript",
      "nid": "behaviour-driven-development-with-javascript",
      "published_at": "2014-09-24 14:37:34"
    },
    {
      "id": 2,
      "name": "The Definitive Guide to the JavaScript Generators",
      "nid": "the-definitive-guide-to-the-javascript-generators",
      "published_at": "2014-10-04 10:58:48"
    },
    {
      "id": 3,
      "name": "Pro AngularJS",
      "nid": "pro-angularjs",
      "published_at": null
    },
    {
      "id": 4,
      "name": "Harder, Better, Faster, Stronger Lo-Dash v3",
      "nid": "harder-better-faster-stronger-lo-dash-v3",
      "published_at": "2015-01-20 14:46:53"
    },
    {
      "id": 6,
      "name": "MySQL SINSERT",
      "nid": "mysql-sinsert",
      "published_at": "2015-04-02 18:18:20"
    },
    {
      "id": 7,
      "name": "The Definitive Guide to the ES7 async functions",
      "nid": "the-definitive-guide-to-the-es7-async-functions",
      "published_at": null
    },
    {
      "id": 8,
      "name": "Using MySQL in Node.js",
      "nid": "using-mysql-in-node-js",
      "published_at": "2016-04-24 17:37:38"
    },
    {
      "id": 9,
      "name": "Using DataLoader to batch requests",
      "nid": "using-dataloader-to-batch-requests",
      "published_at": "2016-08-19 14:59:43"
    }
  ]
}
